{
    "name": "ImpExItemType",
    "enabled": true,
    "aggregation": "FIRST",
    "confidential": false,
    "dataSources": [
        {
            "enabled": true,
            "methods": [
                {
                    "argumentIndex": 0,
                    "capture": "ARGUMENT",
                    "deepObjectAccess": ".class.getSimpleName()",
                    "method": {
                        "argumentTypes": [],
                        "className": "de.hybris.platform.impex.jalo.Importer",
                        "methodName": "importNext",
                        "modifiers": [
                            "FINAL"
                        ],
                        "returnType": "de.hybris.platform.jalo.Item",
                        "visibility": "PUBLIC"
                    }
                }
            ],
            "source": "METHOD_PARAM",
            "technology": "JAVA",
            "valueProcessing": {
                "splitAt": "",
                "trim": false
            }
        }
    ],
    "dataType": "STRING",
    "normalization": "ORIGINAL",
    "skipPersonalDataMasking": false
}